LICENSE
MANIFEST.in
README.md
scrapy.cfg
setup.cfg
setup.py
lich_linkextractor/__init__.py
lich_linkextractor/items.py
lich_linkextractor/middlewares.py
lich_linkextractor/pipelines.py
lich_linkextractor/settings.py
lich_linkextractor/utils.py
lich_linkextractor.egg-info/PKG-INFO
lich_linkextractor.egg-info/SOURCES.txt
lich_linkextractor.egg-info/dependency_links.txt
lich_linkextractor.egg-info/not-zip-safe
lich_linkextractor.egg-info/requires.txt
lich_linkextractor.egg-info/top_level.txt
lich_linkextractor/async_extension/__init__.py
lich_linkextractor/spiders/__init__.py
requirements/requirements-lint.txt
requirements/requirements-test.txt
requirements/requirements.txt
tests/__init__.py
tests/test_scrapy_check.py